draw_palette/__init__.py
draw_palette/config.py
draw_palette/drawer.py
draw_palette/utils.py
draw_palette-0.3.dist-info/METADATA
draw_palette-0.3.dist-info/WHEEL
draw_palette-0.3.dist-info/licenses/LICENSE
draw_palette-0.3.dist-info/RECORD
