Metadata-Version: 2.4
Name: draw_palette
Version: 0.3
Summary: Simple package for rendering image plate a color scheme palette of neovim or anything else
Project-URL: Homepage, https://github.com/romanaverin/draw_palette
Project-URL: Issues, https://github.com/romanaverin/draw_palette/issues
Author-email: Roman Averin <mail@romanaverin.com>
License-Expression: MIT
License-File: LICENSE
Classifier: Programming Language :: Python :: 3
Classifier: Topic :: Multimedia :: Graphics
Classifier: Topic :: Utilities
Requires-Python: >=3.10
Requires-Dist: lupa==2.4
Requires-Dist: matplotlib==3.10.1
